ShenruLijieYii20/README.md
ShenruLijieYii20/__init__.py
ShenruLijieYii20/__main__.py
ShenruLijieYii20/file.epub
ShenruLijieYii20/index.html
ShenruLijieYii20/css/__init__.py
ShenruLijieYii20/css/annotations.css
ShenruLijieYii20/css/main.css
ShenruLijieYii20/css/normalize.css
ShenruLijieYii20/css/popup.css
ShenruLijieYii20/font/__init__.py
ShenruLijieYii20/font/fontello.eot
ShenruLijieYii20/font/fontello.svg
ShenruLijieYii20/font/fontello.ttf
ShenruLijieYii20/font/fontello.woff
ShenruLijieYii20/img/__init__.py
ShenruLijieYii20/img/annotator-glyph-sprite.png
ShenruLijieYii20/img/annotator-icon-sprite.png
ShenruLijieYii20/img/apple-touch-icon.png
ShenruLijieYii20/img/cancelfullscreen.png
ShenruLijieYii20/img/close.png
ShenruLijieYii20/img/fullscreen.png
ShenruLijieYii20/img/loader.gif
ShenruLijieYii20/img/menu-icon.png
ShenruLijieYii20/img/save.png
ShenruLijieYii20/img/saved.png
ShenruLijieYii20/img/settings-s.png
ShenruLijieYii20/img/settings.png
ShenruLijieYii20/img/star.png
ShenruLijieYii20/js/__init__.py
ShenruLijieYii20/js/epub.js
ShenruLijieYii20/js/epub.min.js
ShenruLijieYii20/js/epub.min.map
ShenruLijieYii20/js/hooks.min.js
ShenruLijieYii20/js/hooks.min.map
ShenruLijieYii20/js/reader.js
ShenruLijieYii20/js/reader.js.map
ShenruLijieYii20/js/reader.min.js
ShenruLijieYii20/js/reader.min.map
ShenruLijieYii20/js/hooks/__init__.py
ShenruLijieYii20/js/hooks/extensions/__init__.py
ShenruLijieYii20/js/hooks/extensions/highlight.js
ShenruLijieYii20/js/libs/__init__.py
ShenruLijieYii20/js/libs/jquery.min.js
ShenruLijieYii20/js/libs/localforage.min.js
ShenruLijieYii20/js/libs/screenfull.js
ShenruLijieYii20/js/libs/screenfull.min.js
ShenruLijieYii20/js/libs/zip.min.js
ShenruLijieYii20/js/plugins/__init__.py
ShenruLijieYii20/js/plugins/hypothesis.js
ShenruLijieYii20/js/plugins/search.js
shenru_lijie_yii2_0-2024.3.1.0.dist-info/METADATA
shenru_lijie_yii2_0-2024.3.1.0.dist-info/WHEEL
shenru_lijie_yii2_0-2024.3.1.0.dist-info/entry_points.txt
shenru_lijie_yii2_0-2024.3.1.0.dist-info/top_level.txt
shenru_lijie_yii2_0-2024.3.1.0.dist-info/RECORD
